{
  "ComponentIndexes": {},
  "ControlUniqueGuids": {},
  "ControlUniqueIds": {
    "Amount in figures_DataCard2_5": 118,
    "Amount in figures_DataCard2_6": 583,
    "Amount in figures_DataCard2_7": 46,
    "Amount in figures_DataCard2_8": 256,
    "Amount in figures_DataCard3": 183,
    "Amount in figures_DataCard5_3": 515,
    "Amount in figures_DataCard5_4": 391,
    "Amount in words_DataCard2_5": 123,
    "Amount in words_DataCard2_6": 588,
    "Amount in words_DataCard2_7": 51,
    "Amount in words_DataCard2_8": 261,
    "Amount in words_DataCard3": 188,
    "Amount in words_DataCard5_3": 520,
    "Amount in words_DataCard5_4": 396,
    "AmountInFigures": 186,
    "App": 1,
    "approverOne": 201,
    "Arrow1_1": 449,
    "attachment": 196,
    "attachment_2": 451,
    "Attachments_DataCard2_5": 133,
    "Attachments_DataCard2_6": 603,
    "Attachments_DataCard2_7": 66,
    "Attachments_DataCard2_8": 276,
    "Attachments_DataCard4": 193,
    "Attachments_DataCard5_3": 535,
    "Attachments_DataCard5_4": 411,
    "BottomContainer4": 469,
    "BottomContainer4_1": 345,
    "Button1": 203,
    "Button1_1": 224,
    "Button1_2": 298,
    "Button2": 206,
    "Button2_1": 305,
    "Button2_3": 209,
    "Button2_4": 312,
    "Button3": 212,
    "Button3_1": 315,
    "Button4": 215,
    "Button4_1": 319,
    "Button5": 218,
    "Button5_1": 326,
    "Button5_2": 221,
    "Button5_3": 334,
    "Button6": 83,
    "Button6_1": 85,
    "Button6_2": 16,
    "Button6_3": 17,
    "Button6_4": 288,
    "Button6_5": 289,
    "Button7": 301,
    "Button7_1": 302,
    "Button7_2": 73,
    "Button7_3": 547,
    "Button7_4": 300,
    "Button7_5": 303,
    "Button7_6": 331,
    "Button7_7": 325,
    "Button7_8": 329,
    "comment": 84,
    "comment2": 18,
    "comment3": 290,
    "DataCardKey1": 150,
    "DataCardKey2": 200,
    "DataCardKey21": 145,
    "DataCardKey22": 155,
    "DataCardKey23": 175,
    "DataCardKey24": 185,
    "DataCardKey25": 190,
    "DataCardKey26": 160,
    "DataCardKey27": 165,
    "DataCardKey28": 170,
    "DataCardKey29": 195,
    "DataCardKey3": 180,
    "DataCardKey30_5": 90,
    "DataCardKey30_6": 560,
    "DataCardKey30_7": 23,
    "DataCardKey30_8": 233,
    "DataCardKey31_5": 110,
    "DataCardKey31_6": 580,
    "DataCardKey31_7": 43,
    "DataCardKey31_8": 253,
    "DataCardKey32_5": 120,
    "DataCardKey32_6": 585,
    "DataCardKey32_7": 48,
    "DataCardKey32_8": 258,
    "DataCardKey33_5": 125,
    "DataCardKey33_6": 590,
    "DataCardKey33_7": 53,
    "DataCardKey33_8": 263,
    "DataCardKey34_5": 100,
    "DataCardKey34_6": 570,
    "DataCardKey34_7": 33,
    "DataCardKey34_8": 243,
    "DataCardKey36_5": 105,
    "DataCardKey36_6": 575,
    "DataCardKey36_7": 38,
    "DataCardKey36_8": 248,
    "DataCardKey39_5": 95,
    "DataCardKey39_6": 565,
    "DataCardKey39_7": 28,
    "DataCardKey39_8": 238,
    "DataCardKey40_5": 115,
    "DataCardKey40_6": 595,
    "DataCardKey40_7": 58,
    "DataCardKey40_8": 268,
    "DataCardKey42_5": 130,
    "DataCardKey42_6": 600,
    "DataCardKey42_7": 63,
    "DataCardKey42_8": 273,
    "DataCardKey44_5": 135,
    "DataCardKey44_6": 605,
    "DataCardKey44_7": 68,
    "DataCardKey44_8": 278,
    "DataCardKey62_3": 487,
    "DataCardKey62_4": 363,
    "DataCardKey63_3": 507,
    "DataCardKey63_4": 383,
    "DataCardKey64_3": 517,
    "DataCardKey64_4": 393,
    "DataCardKey65_3": 522,
    "DataCardKey65_4": 398,
    "DataCardKey66_3": 497,
    "DataCardKey66_4": 373,
    "DataCardKey68_3": 502,
    "DataCardKey68_4": 378,
    "DataCardKey71_3": 492,
    "DataCardKey71_4": 368,
    "DataCardKey72_3": 512,
    "DataCardKey72_4": 388,
    "DataCardKey75_3": 527,
    "DataCardKey75_4": 403,
    "DataCardKey76_3": 537,
    "DataCardKey76_4": 413,
    "DataCardKey77_3": 532,
    "DataCardKey77_4": 408,
    "DataCardValue1": 151,
    "DataCardValue2": 181,
    "DataCardValue20_5": 91,
    "DataCardValue20_6": 561,
    "DataCardValue20_7": 24,
    "DataCardValue20_8": 234,
    "DataCardValue21": 146,
    "DataCardValue22": 156,
    "DataCardValue23": 176,
    "DataCardValue25": 191,
    "DataCardValue26": 161,
    "DataCardValue27": 166,
    "DataCardValue28": 171,
    "DataCardValue29_5": 111,
    "DataCardValue29_6": 581,
    "DataCardValue29_7": 44,
    "DataCardValue29_8": 254,
    "DataCardValue30_5": 121,
    "DataCardValue30_6": 586,
    "DataCardValue30_7": 49,
    "DataCardValue30_8": 259,
    "DataCardValue31_5": 126,
    "DataCardValue31_6": 591,
    "DataCardValue31_7": 54,
    "DataCardValue31_8": 264,
    "DataCardValue32_5": 101,
    "DataCardValue32_6": 571,
    "DataCardValue32_7": 34,
    "DataCardValue32_8": 244,
    "DataCardValue34_5": 106,
    "DataCardValue34_6": 576,
    "DataCardValue34_7": 39,
    "DataCardValue34_8": 249,
    "DataCardValue37_5": 96,
    "DataCardValue37_6": 566,
    "DataCardValue37_7": 29,
    "DataCardValue37_8": 239,
    "DataCardValue38_5": 116,
    "DataCardValue38_6": 596,
    "DataCardValue38_7": 59,
    "DataCardValue38_8": 269,
    "DataCardValue42_5": 136,
    "DataCardValue42_6": 606,
    "DataCardValue42_7": 69,
    "DataCardValue42_8": 279,
    "DataCardValue60_3": 488,
    "DataCardValue60_4": 364,
    "DataCardValue61_3": 508,
    "DataCardValue61_4": 384,
    "DataCardValue62_3": 518,
    "DataCardValue62_4": 394,
    "DataCardValue63_3": 523,
    "DataCardValue63_4": 399,
    "DataCardValue64_3": 498,
    "DataCardValue64_4": 374,
    "DataCardValue66_3": 503,
    "DataCardValue66_4": 379,
    "DataCardValue69_3": 493,
    "DataCardValue69_4": 369,
    "DataCardValue70_3": 513,
    "DataCardValue70_4": 389,
    "DataCardValue73_3": 528,
    "DataCardValue73_4": 404,
    "DataCardValue74_3": 538,
    "DataCardValue74_4": 414,
    "DataCardValue75_3": 533,
    "DataCardValue75_4": 409,
    "Date_DataCard1": 148,
    "Date_DataCard3_5": 93,
    "Date_DataCard3_6": 563,
    "Date_DataCard3_7": 26,
    "Date_DataCard3_8": 236,
    "Date_DataCard5_3": 490,
    "Date_DataCard5_4": 366,
    "Department_DataCard2_5": 98,
    "Department_DataCard2_6": 568,
    "Department_DataCard2_7": 31,
    "Department_DataCard2_8": 241,
    "Department_DataCard4": 158,
    "Department_DataCard5_3": 495,
    "Department_DataCard5_4": 371,
    "ErrorMessage1": 152,
    "ErrorMessage2": 202,
    "ErrorMessage21": 147,
    "ErrorMessage22": 157,
    "ErrorMessage23": 177,
    "ErrorMessage24": 187,
    "ErrorMessage25": 192,
    "ErrorMessage26": 162,
    "ErrorMessage27": 167,
    "ErrorMessage28": 172,
    "ErrorMessage29": 197,
    "ErrorMessage3": 182,
    "ErrorMessage30_5": 92,
    "ErrorMessage30_6": 562,
    "ErrorMessage30_7": 25,
    "ErrorMessage30_8": 235,
    "ErrorMessage31_5": 112,
    "ErrorMessage31_6": 582,
    "ErrorMessage31_7": 45,
    "ErrorMessage31_8": 255,
    "ErrorMessage32_5": 122,
    "ErrorMessage32_6": 587,
    "ErrorMessage32_7": 50,
    "ErrorMessage32_8": 260,
    "ErrorMessage33_5": 127,
    "ErrorMessage33_6": 592,
    "ErrorMessage33_7": 55,
    "ErrorMessage33_8": 265,
    "ErrorMessage34_5": 102,
    "ErrorMessage34_6": 572,
    "ErrorMessage34_7": 35,
    "ErrorMessage34_8": 245,
    "ErrorMessage36_5": 107,
    "ErrorMessage36_6": 577,
    "ErrorMessage36_7": 40,
    "ErrorMessage36_8": 250,
    "ErrorMessage39_5": 97,
    "ErrorMessage39_6": 567,
    "ErrorMessage39_7": 30,
    "ErrorMessage39_8": 240,
    "ErrorMessage40_5": 117,
    "ErrorMessage40_6": 597,
    "ErrorMessage40_7": 60,
    "ErrorMessage40_8": 270,
    "ErrorMessage42_5": 132,
    "ErrorMessage42_6": 602,
    "ErrorMessage42_7": 65,
    "ErrorMessage42_8": 275,
    "ErrorMessage44_5": 137,
    "ErrorMessage44_6": 607,
    "ErrorMessage44_7": 70,
    "ErrorMessage44_8": 280,
    "ErrorMessage62_3": 489,
    "ErrorMessage62_4": 365,
    "ErrorMessage63_3": 509,
    "ErrorMessage63_4": 385,
    "ErrorMessage64_3": 519,
    "ErrorMessage64_4": 395,
    "ErrorMessage65_3": 524,
    "ErrorMessage65_4": 400,
    "ErrorMessage66_3": 499,
    "ErrorMessage66_4": 375,
    "ErrorMessage68_3": 504,
    "ErrorMessage68_4": 380,
    "ErrorMessage71_3": 494,
    "ErrorMessage71_4": 370,
    "ErrorMessage72_3": 514,
    "ErrorMessage72_4": 390,
    "ErrorMessage75_3": 529,
    "ErrorMessage75_4": 405,
    "ErrorMessage76_3": 539,
    "ErrorMessage76_4": 415,
    "ErrorMessage77_3": 534,
    "ErrorMessage77_4": 410,
    "Expense Category_DataCard2_5": 103,
    "Expense Category_DataCard2_6": 573,
    "Expense Category_DataCard2_7": 36,
    "Expense Category_DataCard2_8": 246,
    "Expense Category_DataCard3": 168,
    "Expense Category_DataCard5_3": 500,
    "Expense Category_DataCard5_4": 376,
    "Form1": 142,
    "Form3_5": 87,
    "Form3_6": 557,
    "Form3_7": 20,
    "Form3_8": 230,
    "Form5_3": 484,
    "Form5_4": 360,
    "Gallery1": 76,
    "Gallery1_1": 549,
    "Gallery1_2": 9,
    "Gallery1_3": 281,
    "Gallery5_2": 471,
    "Gallery5_4": 347,
    "Gallery5_5": 453,
    "galleryTemplate1": 77,
    "galleryTemplate1_1": 550,
    "galleryTemplate1_2": 10,
    "galleryTemplate1_3": 282,
    "galleryTemplate5_2": 472,
    "galleryTemplate5_4": 348,
    "galleryTemplate5_5": 454,
    "HeaderContainer4": 467,
    "HeaderContainer4_1": 342,
    "HOD Dashboard": 71,
    "HOD Dashboard_Pending": 544,
    "HOD email address_1": 131,
    "HOD email address_2": 601,
    "HOD email address_3": 64,
    "HOD email address_4": 274,
    "HOD/Proxy HOD email address_DataCard1": 198,
    "HOD/Proxy HOD email address_DataCard3_5": 128,
    "HOD/Proxy HOD email address_DataCard3_6": 598,
    "HOD/Proxy HOD email address_DataCard3_7": 61,
    "HOD/Proxy HOD email address_DataCard3_8": 271,
    "HOD/Proxy HOD email address_DataCard6_3": 530,
    "HOD/Proxy HOD email address_DataCard6_4": 406,
    "Host": 3,
    "HR Dashboard": 4,
    "Icon1": 204,
    "Icon1_1": 299,
    "Icon1_2": 74,
    "Icon1_3": 546,
    "Icon1_4": 8,
    "Icon1_5": 228,
    "Icon10": 420,
    "Icon11_1": 452,
    "Icon12_1": 450,
    "Icon14": 337,
    "Icon17": 222,
    "Icon2": 213,
    "Icon2_1": 316,
    "Icon3": 207,
    "Icon3_1": 309,
    "Icon4": 210,
    "Icon4_1": 313,
    "Icon5": 540,
    "Icon5_1": 416,
    "Icon6": 542,
    "Icon6_1": 418,
    "Icon7": 216,
    "Icon7_1": 320,
    "Icon8": 220,
    "Icon8_1": 328,
    "Image1": 141,
    "Image2": 138,
    "Image2_1": 425,
    "Image3": 6,
    "Image3_1": 227,
    "Image4": 541,
    "Image4_1": 417,
    "Image5": 294,
    "Image8": 543,
    "Image8_1": 421,
    "Item_DataCard2_5": 108,
    "Item_DataCard2_6": 578,
    "Item_DataCard2_7": 41,
    "Item_DataCard2_8": 251,
    "Item_DataCard3": 173,
    "Item_DataCard5_3": 505,
    "Item_DataCard5_4": 381,
    "Label1": 205,
    "Label1_1": 304,
    "Label10": 427,
    "Label10_1": 428,
    "Label10_10": 441,
    "Label10_11": 442,
    "Label10_12": 431,
    "Label10_2": 429,
    "Label10_3": 430,
    "Label10_4": 432,
    "Label10_5": 434,
    "Label10_6": 436,
    "Label10_7": 435,
    "Label10_8": 438,
    "Label10_9": 439,
    "Label11": 433,
    "Label11_1": 437,
    "Label11_2": 440,
    "Label11_3": 443,
    "Label13": 324,
    "Label13_1": 318,
    "Label13_2": 323,
    "Label13_3": 322,
    "Label13_4": 339,
    "Label13_5": 338,
    "Label13_6": 332,
    "Label14_1": 446,
    "Label14_2": 445,
    "Label15": 307,
    "Label15_1": 333,
    "Label15_2": 311,
    "Label15_3": 330,
    "Label16": 335,
    "Label17": 296,
    "Label2": 208,
    "Label2_1": 310,
    "Label2_2": 211,
    "Label2_3": 314,
    "Label3": 217,
    "Label3_1": 321,
    "Label3_2": 336,
    "Label4": 426,
    "Label5": 219,
    "Label5_1": 327,
    "Label5_2": 223,
    "Label6": 306,
    "Label6_2": 75,
    "Label6_3": 548,
    "Label7": 308,
    "Label7_1": 7,
    "Label8": 214,
    "Label8_1": 317,
    "Label9": 297,
    "Label9_1": 229,
    "LblAppName1_10": 5,
    "LblAppName1_11": 226,
    "LblAppName1_8": 72,
    "LblAppName1_9": 545,
    "LblAppName2_1": 468,
    "LblAppName2_2": 343,
    "MainContainer4": 483,
    "MainContainer4_1": 359,
    "MD Dashboard": 225,
    "Name of Employee_DataCard2_5": 88,
    "Name of Employee_DataCard2_6": 558,
    "Name of Employee_DataCard2_7": 21,
    "Name of Employee_DataCard2_8": 231,
    "Name of Employee_DataCard3": 153,
    "Name of Employee_DataCard5_3": 485,
    "Name of Employee_DataCard5_4": 361,
    "New Request Screen": 139,
    "NextArrow1": 81,
    "NextArrow1_1": 555,
    "NextArrow1_2": 14,
    "NextArrow1_3": 286,
    "NextArrow5_2": 477,
    "NextArrow5_4": 353,
    "NextArrow5_5": 459,
    "Overall Request": 340,
    "Past Requests": 465,
    "pdfPane_1": 424,
    "Quantity_DataCard1": 178,
    "Quantity_DataCard3_5": 113,
    "Quantity_DataCard3_6": 593,
    "Quantity_DataCard3_7": 56,
    "Quantity_DataCard3_8": 266,
    "Quantity_DataCard5_3": 510,
    "Quantity_DataCard5_4": 386,
    "Receipt Confirmation Screen": 422,
    "Rectangle1": 78,
    "Rectangle1_1": 140,
    "Rectangle1_2": 293,
    "Rectangle1_3": 551,
    "Rectangle1_4": 11,
    "Rectangle1_5": 283,
    "Rectangle2": 295,
    "Rectangle3": 444,
    "Rectangle4": 447,
    "Rectangle4_1": 448,
    "Rectangle5_2": 473,
    "Rectangle5_4": 349,
    "Rectangle5_5": 455,
    "Report": 292,
    "Request Type_DataCard3": 163,
    "ScreenContainer4": 466,
    "ScreenContainer4_1": 341,
    "Separator1": 86,
    "Separator1_1": 556,
    "Separator1_2": 19,
    "Separator1_3": 291,
    "Separator5_2": 482,
    "Separator5_4": 358,
    "Separator5_5": 464,
    "SidebarContainer4": 470,
    "SidebarContainer4_1": 346,
    "StarVisible1": 149,
    "StarVisible2": 199,
    "StarVisible21": 144,
    "StarVisible22": 154,
    "StarVisible23": 174,
    "StarVisible24": 184,
    "StarVisible25": 189,
    "StarVisible26": 159,
    "StarVisible27": 164,
    "StarVisible28": 169,
    "StarVisible29": 194,
    "StarVisible3": 179,
    "StarVisible30_5": 89,
    "StarVisible30_6": 559,
    "StarVisible30_7": 22,
    "StarVisible30_8": 232,
    "StarVisible31_5": 109,
    "StarVisible31_6": 579,
    "StarVisible31_7": 42,
    "StarVisible31_8": 252,
    "StarVisible32_5": 119,
    "StarVisible32_6": 584,
    "StarVisible32_7": 47,
    "StarVisible32_8": 257,
    "StarVisible33_5": 124,
    "StarVisible33_6": 589,
    "StarVisible33_7": 52,
    "StarVisible33_8": 262,
    "StarVisible34_5": 99,
    "StarVisible34_6": 569,
    "StarVisible34_7": 32,
    "StarVisible34_8": 242,
    "StarVisible36_5": 104,
    "StarVisible36_6": 574,
    "StarVisible36_7": 37,
    "StarVisible36_8": 247,
    "StarVisible39_5": 94,
    "StarVisible39_6": 564,
    "StarVisible39_7": 27,
    "StarVisible39_8": 237,
    "StarVisible40_5": 114,
    "StarVisible40_6": 594,
    "StarVisible40_7": 57,
    "StarVisible40_8": 267,
    "StarVisible42_5": 129,
    "StarVisible42_6": 599,
    "StarVisible42_7": 62,
    "StarVisible42_8": 272,
    "StarVisible44_5": 134,
    "StarVisible44_6": 604,
    "StarVisible44_7": 67,
    "StarVisible44_8": 277,
    "StarVisible62_3": 486,
    "StarVisible62_4": 362,
    "StarVisible63_3": 506,
    "StarVisible63_4": 382,
    "StarVisible64_3": 516,
    "StarVisible64_4": 392,
    "StarVisible65_3": 521,
    "StarVisible65_4": 397,
    "StarVisible66_3": 496,
    "StarVisible66_4": 372,
    "StarVisible68_3": 501,
    "StarVisible68_4": 377,
    "StarVisible71_3": 491,
    "StarVisible71_4": 367,
    "StarVisible72_3": 511,
    "StarVisible72_4": 387,
    "StarVisible75_3": 526,
    "StarVisible75_4": 402,
    "StarVisible76_3": 536,
    "StarVisible76_4": 412,
    "StarVisible77_3": 531,
    "StarVisible77_4": 407,
    "Status_DataCard4_3": 525,
    "Status_DataCard4_4": 401,
    "Subtitle1": 80,
    "Subtitle1_1": 553,
    "Subtitle1_2": 13,
    "Subtitle1_3": 285,
    "Subtitle5_14": 476,
    "Subtitle5_16": 352,
    "Subtitle5_17": 458,
    "Subtitle5_18": 478,
    "Subtitle5_19": 479,
    "Subtitle5_20": 480,
    "Subtitle5_24": 354,
    "Subtitle5_25": 355,
    "Subtitle5_26": 356,
    "Subtitle5_27": 481,
    "Subtitle5_29": 357,
    "Subtitle5_30": 460,
    "Subtitle5_31": 462,
    "Subtitle5_32": 463,
    "Subtitle5_33": 461,
    "Subtitle5_5": 474,
    "Subtitle5_7": 350,
    "Subtitle5_8": 456,
    "TextInput1_1": 423,
    "TextInput4": 344,
    "TextInput5": 419,
    "Title_DataCard3": 143,
    "Title1": 79,
    "Title1_1": 82,
    "Title1_2": 552,
    "Title1_3": 554,
    "Title1_4": 12,
    "Title1_5": 15,
    "Title1_6": 284,
    "Title1_7": 287,
    "Title5_2": 475,
    "Title5_4": 351,
    "Title5_5": 457
  },
  "FunctionParamsInvariantScripts": {},
  "FunctionParamsInvariantScriptsOnInstances": {},
  "HeaderLastSavedDateTimeUTC": "09/01/2023 14:59:43",
  "IsLegacyComponentAllowGlobalScopeCase": false,
  "LocalConnectionIDReferences": {
    "9c62eb33-2788-460f-803d-a3cfb362e426": "\"/providers/microsoft.powerapps/apis/shared_sharepointonline/connections/shared-sharepointonl-685e30cd-e36f-4690-a21e-09842964fa5a\"",
    "be59c901-b378-4f62-9a8d-23026181bc1b": "\"/providers/microsoft.powerapps/apis/shared_office365/connections/7f71b3dfd8aa45b9864af4971ffba7ab\""
  },
  "LocalDatabaseReferencesAsEmpty": false,
  "LocalResourceFileNames": {
    "3652191": "9126c91a-d36c-4944-950d-eec3beb05dfe.png",
    "4221459": "95f4285a-239c-49ea-a684-677eff0e75a5.png",
    "approve-badge-4715768": "84545be6-1149-4a84-b277-4e908cd3e11d.png",
    "approved-checklist-5588674": "0c5a7d14-e18d-4301-b79b-41a8262df598.png",
    "check-profile-4715752": "3b94a015-3a73-44ed-9688-d93d06b68241.png",
    "DD": "f5c1a097-d472-413b-809e-cf1b11b985d2.png",
    "dd white": "b9784dfa-32a3-4129-8850-036051ca0e9e.png",
    "images": "94cc9c81-222a-49fa-9d36-62095849b95d.png",
    "nr1": "f10ae384-cf2e-4c05-bebb-21f2f75319a3.png",
    "verified-calendar-5575938": "b462608e-ef80-426d-9aa7-a158f30df8f1.png"
  },
  "LocalResourceRootPaths": {
    "3652191": "https://docserverpwaprodweu.blob.core.windows.net/08030af9-2b49-4d4f-b2b1-e3391341c218-1/resource/Assets0Images09126c91a-d36c-4944-950d-eec3beb05dfe.png?sv=2018-03-28&sr=b&sig=ju%2B8qCN5nn9%2FW5tDVXZKko%2FbBGNXTXtoY8MTQn8XVko%3D&spr=https&se=2023-09-02T10%3A55%3A43Z&sp=r",
    "4221459": "https://docserverpwaprodweu.blob.core.windows.net/08030af9-2b49-4d4f-b2b1-e3391341c218-1/resource/Assets0Images095f4285a-239c-49ea-a684-677eff0e75a5.png?sv=2018-03-28&sr=b&sig=k6cGeIjMPm2DoanbdOqzxFbinMHZB%2BNwMbJOQsnM2j4%3D&spr=https&se=2023-09-02T10%3A55%3A43Z&sp=r",
    "approve-badge-4715768": "https://docserverpwaprodweu.blob.core.windows.net/08030af9-2b49-4d4f-b2b1-e3391341c218-1/resource/Assets0Images084545be6-1149-4a84-b277-4e908cd3e11d.png?sv=2018-03-28&sr=b&sig=1yD8tdPafELcCqkYam4P%2BS7IvfHFNk%2BZQfvwVF%2Boibo%3D&spr=https&se=2023-09-02T10%3A55%3A43Z&sp=r",
    "approved-checklist-5588674": "https://docserverpwaprodweu.blob.core.windows.net/08030af9-2b49-4d4f-b2b1-e3391341c218-1/resource/Assets0Images00c5a7d14-e18d-4301-b79b-41a8262df598.png?sv=2018-03-28&sr=b&sig=ZKcuvk9B7hijYeBq%2BF5j504V5KdUq8J0oXp%2BC6YHjSE%3D&spr=https&se=2023-09-02T10%3A55%3A43Z&sp=r",
    "check-profile-4715752": "https://docserverpwaprodweu.blob.core.windows.net/08030af9-2b49-4d4f-b2b1-e3391341c218-1/resource/Assets0Images03b94a015-3a73-44ed-9688-d93d06b68241.png?sv=2018-03-28&sr=b&sig=ssqUgxzbS%2BscdPph0dJioBqwjC%2BF8YmJ6BI9zsMtHwU%3D&spr=https&se=2023-09-02T10%3A55%3A43Z&sp=r",
    "DD": "https://docserverpwaprodweu.blob.core.windows.net/08030af9-2b49-4d4f-b2b1-e3391341c218-1/resource/Assets0Images0f5c1a097-d472-413b-809e-cf1b11b985d2.png?sv=2018-03-28&sr=b&sig=5POlJ0P7RKtuygzLL9UQvJoxCH3MS25YxZqV63LlLeE%3D&spr=https&se=2023-09-02T10%3A55%3A43Z&sp=r",
    "dd white": "https://docserverpwaprodweu.blob.core.windows.net/08030af9-2b49-4d4f-b2b1-e3391341c218-1/resource/Assets0Images0b9784dfa-32a3-4129-8850-036051ca0e9e.png?sv=2018-03-28&sr=b&sig=hrHy5aznAAOfzSyfEPv1CMNMdl83D7Dql2xWKMhOV7w%3D&spr=https&se=2023-09-02T10%3A55%3A43Z&sp=r",
    "images": "https://docserverpwaprodweu.blob.core.windows.net/08030af9-2b49-4d4f-b2b1-e3391341c218-1/resource/Assets0Images094cc9c81-222a-49fa-9d36-62095849b95d.png?sv=2018-03-28&sr=b&sig=u3epXidkdyNULLMwF%2Bae7vxyH1m0OZV3scioJ0di2mM%3D&spr=https&se=2023-09-02T10%3A55%3A43Z&sp=r",
    "nr1": "https://docserverpwaprodweu.blob.core.windows.net/08030af9-2b49-4d4f-b2b1-e3391341c218-1/resource/Assets0Images0f10ae384-cf2e-4c05-bebb-21f2f75319a3.png?sv=2018-03-28&sr=b&sig=i7Fm5J84ju%2BLemPZGyDg7ZK%2FR451XabpJo4EYSRsszM%3D&spr=https&se=2023-09-02T10%3A55%3A43Z&sp=r",
    "verified-calendar-5575938": "https://docserverpwaprodweu.blob.core.windows.net/08030af9-2b49-4d4f-b2b1-e3391341c218-1/resource/Assets0Images0b462608e-ef80-426d-9aa7-a158f30df8f1.png?sv=2018-03-28&sr=b&sig=tjXbY95QMZltrs%2BrQOcZmofjcZ8jk%2Bbw4ILXPXAxt9U%3D&spr=https&se=2023-09-02T10%3A55%3A43Z&sp=r"
  },
  "OldLogoFileName": "zpdneggi.jpg",
  "OrderComponentMetadata": {},
  "OrderComponentTemplate": {},
  "OrderDataSource": {
    "Cash Requisition Form Sharepoint": 1,
    "ComboBoxSample": 2,
    "CustomGallerySample": 3,
    "Office365Outlook": 0
  },
  "OrderGroupControls": {},
  "OrderPcfTemplate": {},
  "OrderTemplate": {},
  "OrderXMLTemplate": {
    "arrow": 12,
    "attachments": 10,
    "button": 5,
    "combobox": 9,
    "datepicker": 8,
    "form": 7,
    "gallery": 3,
    "groupContainer": 11,
    "icon": 2,
    "image": 1,
    "label": 0,
    "rectangle": 4,
    "text": 6
  },
  "OverridablePropertiesEntry": {
    "Amount in figures_DataCard2_5": {},
    "Amount in figures_DataCard2_6": {},
    "Amount in figures_DataCard2_7": {},
    "Amount in figures_DataCard2_8": {},
    "Amount in figures_DataCard3": {},
    "Amount in figures_DataCard5_3": {},
    "Amount in figures_DataCard5_4": {},
    "Amount in words_DataCard2_5": {},
    "Amount in words_DataCard2_6": {},
    "Amount in words_DataCard2_7": {},
    "Amount in words_DataCard2_8": {},
    "Amount in words_DataCard3": {},
    "Amount in words_DataCard5_3": {},
    "Amount in words_DataCard5_4": {},
    "AmountInFigures": {},
    "App": {},
    "approverOne": {},
    "Arrow1_1": {},
    "attachment": {},
    "attachment_2": {},
    "Attachments_DataCard2_5": {},
    "Attachments_DataCard2_6": {},
    "Attachments_DataCard2_7": {},
    "Attachments_DataCard2_8": {},
    "Attachments_DataCard4": {},
    "Attachments_DataCard5_3": {},
    "Attachments_DataCard5_4": {},
    "BottomContainer4": {},
    "BottomContainer4_1": {},
    "Button1": {},
    "Button1_1": {},
    "Button1_2": {},
    "Button2": {},
    "Button2_1": {},
    "Button2_3": {},
    "Button2_4": {},
    "Button3": {},
    "Button3_1": {},
    "Button4": {},
    "Button4_1": {},
    "Button5": {},
    "Button5_1": {},
    "Button5_2": {},
    "Button5_3": {},
    "Button6": {},
    "Button6_1": {},
    "Button6_2": {},
    "Button6_3": {},
    "Button6_4": {},
    "Button6_5": {},
    "Button7": {},
    "Button7_1": {},
    "Button7_2": {},
    "Button7_3": {},
    "Button7_4": {},
    "Button7_5": {},
    "Button7_6": {},
    "Button7_7": {},
    "Button7_8": {},
    "comment": {},
    "comment2": {},
    "comment3": {},
    "DataCardKey1": {},
    "DataCardKey2": {},
    "DataCardKey21": {},
    "DataCardKey22": {},
    "DataCardKey23": {},
    "DataCardKey24": {},
    "DataCardKey25": {},
    "DataCardKey26": {},
    "DataCardKey27": {},
    "DataCardKey28": {},
    "DataCardKey29": {},
    "DataCardKey3": {},
    "DataCardKey30_5": {},
    "DataCardKey30_6": {},
    "DataCardKey30_7": {},
    "DataCardKey30_8": {},
    "DataCardKey31_5": {},
    "DataCardKey31_6": {},
    "DataCardKey31_7": {},
    "DataCardKey31_8": {},
    "DataCardKey32_5": {},
    "DataCardKey32_6": {},
    "DataCardKey32_7": {},
    "DataCardKey32_8": {},
    "DataCardKey33_5": {},
    "DataCardKey33_6": {},
    "DataCardKey33_7": {},
    "DataCardKey33_8": {},
    "DataCardKey34_5": {},
    "DataCardKey34_6": {},
    "DataCardKey34_7": {},
    "DataCardKey34_8": {},
    "DataCardKey36_5": {},
    "DataCardKey36_6": {},
    "DataCardKey36_7": {},
    "DataCardKey36_8": {},
    "DataCardKey39_5": {},
    "DataCardKey39_6": {},
    "DataCardKey39_7": {},
    "DataCardKey39_8": {},
    "DataCardKey40_5": {},
    "DataCardKey40_6": {},
    "DataCardKey40_7": {},
    "DataCardKey40_8": {},
    "DataCardKey42_5": {},
    "DataCardKey42_6": {},
    "DataCardKey42_7": {},
    "DataCardKey42_8": {},
    "DataCardKey44_5": {},
    "DataCardKey44_6": {},
    "DataCardKey44_7": {},
    "DataCardKey44_8": {},
    "DataCardKey62_3": {},
    "DataCardKey62_4": {},
    "DataCardKey63_3": {},
    "DataCardKey63_4": {},
    "DataCardKey64_3": {},
    "DataCardKey64_4": {},
    "DataCardKey65_3": {},
    "DataCardKey65_4": {},
    "DataCardKey66_3": {},
    "DataCardKey66_4": {},
    "DataCardKey68_3": {},
    "DataCardKey68_4": {},
    "DataCardKey71_3": {},
    "DataCardKey71_4": {},
    "DataCardKey72_3": {},
    "DataCardKey72_4": {},
    "DataCardKey75_3": {},
    "DataCardKey75_4": {},
    "DataCardKey76_3": {},
    "DataCardKey76_4": {},
    "DataCardKey77_3": {},
    "DataCardKey77_4": {},
    "DataCardValue1": {},
    "DataCardValue2": {},
    "DataCardValue20_5": {},
    "DataCardValue20_6": {},
    "DataCardValue20_7": {},
    "DataCardValue20_8": {},
    "DataCardValue21": {},
    "DataCardValue22": {},
    "DataCardValue23": {},
    "DataCardValue25": {},
    "DataCardValue26": {},
    "DataCardValue27": {},
    "DataCardValue28": {},
    "DataCardValue29_5": {},
    "DataCardValue29_6": {},
    "DataCardValue29_7": {},
    "DataCardValue29_8": {},
    "DataCardValue30_5": {},
    "DataCardValue30_6": {},
    "DataCardValue30_7": {},
    "DataCardValue30_8": {},
    "DataCardValue31_5": {},
    "DataCardValue31_6": {},
    "DataCardValue31_7": {},
    "DataCardValue31_8": {},
    "DataCardValue32_5": {},
    "DataCardValue32_6": {},
    "DataCardValue32_7": {},
    "DataCardValue32_8": {},
    "DataCardValue34_5": {},
    "DataCardValue34_6": {},
    "DataCardValue34_7": {},
    "DataCardValue34_8": {},
    "DataCardValue37_5": {},
    "DataCardValue37_6": {},
    "DataCardValue37_7": {},
    "DataCardValue37_8": {},
    "DataCardValue38_5": {},
    "DataCardValue38_6": {},
    "DataCardValue38_7": {},
    "DataCardValue38_8": {},
    "DataCardValue42_5": {},
    "DataCardValue42_6": {},
    "DataCardValue42_7": {},
    "DataCardValue42_8": {},
    "DataCardValue60_3": {},
    "DataCardValue60_4": {},
    "DataCardValue61_3": {},
    "DataCardValue61_4": {},
    "DataCardValue62_3": {},
    "DataCardValue62_4": {},
    "DataCardValue63_3": {},
    "DataCardValue63_4": {},
    "DataCardValue64_3": {},
    "DataCardValue64_4": {},
    "DataCardValue66_3": {},
    "DataCardValue66_4": {},
    "DataCardValue69_3": {},
    "DataCardValue69_4": {},
    "DataCardValue70_3": {},
    "DataCardValue70_4": {},
    "DataCardValue73_3": {},
    "DataCardValue73_4": {},
    "DataCardValue74_3": {},
    "DataCardValue74_4": {},
    "DataCardValue75_3": {},
    "DataCardValue75_4": {},
    "Date_DataCard1": {},
    "Date_DataCard3_5": {},
    "Date_DataCard3_6": {},
    "Date_DataCard3_7": {},
    "Date_DataCard3_8": {},
    "Date_DataCard5_3": {},
    "Date_DataCard5_4": {},
    "Department_DataCard2_5": {},
    "Department_DataCard2_6": {},
    "Department_DataCard2_7": {},
    "Department_DataCard2_8": {},
    "Department_DataCard4": {},
    "Department_DataCard5_3": {},
    "Department_DataCard5_4": {},
    "ErrorMessage1": {},
    "ErrorMessage2": {},
    "ErrorMessage21": {},
    "ErrorMessage22": {},
    "ErrorMessage23": {},
    "ErrorMessage24": {},
    "ErrorMessage25": {},
    "ErrorMessage26": {},
    "ErrorMessage27": {},
    "ErrorMessage28": {},
    "ErrorMessage29": {},
    "ErrorMessage3": {},
    "ErrorMessage30_5": {},
    "ErrorMessage30_6": {},
    "ErrorMessage30_7": {},
    "ErrorMessage30_8": {},
    "ErrorMessage31_5": {},
    "ErrorMessage31_6": {},
    "ErrorMessage31_7": {},
    "ErrorMessage31_8": {},
    "ErrorMessage32_5": {},
    "ErrorMessage32_6": {},
    "ErrorMessage32_7": {},
    "ErrorMessage32_8": {},
    "ErrorMessage33_5": {},
    "ErrorMessage33_6": {},
    "ErrorMessage33_7": {},
    "ErrorMessage33_8": {},
    "ErrorMessage34_5": {},
    "ErrorMessage34_6": {},
    "ErrorMessage34_7": {},
    "ErrorMessage34_8": {},
    "ErrorMessage36_5": {},
    "ErrorMessage36_6": {},
    "ErrorMessage36_7": {},
    "ErrorMessage36_8": {},
    "ErrorMessage39_5": {},
    "ErrorMessage39_6": {},
    "ErrorMessage39_7": {},
    "ErrorMessage39_8": {},
    "ErrorMessage40_5": {},
    "ErrorMessage40_6": {},
    "ErrorMessage40_7": {},
    "ErrorMessage40_8": {},
    "ErrorMessage42_5": {},
    "ErrorMessage42_6": {},
    "ErrorMessage42_7": {},
    "ErrorMessage42_8": {},
    "ErrorMessage44_5": {},
    "ErrorMessage44_6": {},
    "ErrorMessage44_7": {},
    "ErrorMessage44_8": {},
    "ErrorMessage62_3": {},
    "ErrorMessage62_4": {},
    "ErrorMessage63_3": {},
    "ErrorMessage63_4": {},
    "ErrorMessage64_3": {},
    "ErrorMessage64_4": {},
    "ErrorMessage65_3": {},
    "ErrorMessage65_4": {},
    "ErrorMessage66_3": {},
    "ErrorMessage66_4": {},
    "ErrorMessage68_3": {},
    "ErrorMessage68_4": {},
    "ErrorMessage71_3": {},
    "ErrorMessage71_4": {},
    "ErrorMessage72_3": {},
    "ErrorMessage72_4": {},
    "ErrorMessage75_3": {},
    "ErrorMessage75_4": {},
    "ErrorMessage76_3": {},
    "ErrorMessage76_4": {},
    "ErrorMessage77_3": {},
    "ErrorMessage77_4": {},
    "Expense Category_DataCard2_5": {},
    "Expense Category_DataCard2_6": {},
    "Expense Category_DataCard2_7": {},
    "Expense Category_DataCard2_8": {},
    "Expense Category_DataCard3": {},
    "Expense Category_DataCard5_3": {},
    "Expense Category_DataCard5_4": {},
    "Form1": {},
    "Form3_5": {},
    "Form3_6": {},
    "Form3_7": {},
    "Form3_8": {},
    "Form5_3": {},
    "Form5_4": {},
    "Gallery1": {},
    "Gallery1_1": {},
    "Gallery1_2": {},
    "Gallery1_3": {},
    "Gallery5_2": {},
    "Gallery5_4": {},
    "Gallery5_5": {},
    "galleryTemplate1": {},
    "galleryTemplate1_1": {},
    "galleryTemplate1_2": {},
    "galleryTemplate1_3": {},
    "galleryTemplate5_2": {},
    "galleryTemplate5_4": {},
    "galleryTemplate5_5": {},
    "HeaderContainer4": {},
    "HeaderContainer4_1": {},
    "HOD Dashboard": {},
    "HOD Dashboard_Pending": {},
    "HOD email address_1": {},
    "HOD email address_2": {},
    "HOD email address_3": {},
    "HOD email address_4": {},
    "HOD/Proxy HOD email address_DataCard1": {},
    "HOD/Proxy HOD email address_DataCard3_5": {},
    "HOD/Proxy HOD email address_DataCard3_6": {},
    "HOD/Proxy HOD email address_DataCard3_7": {},
    "HOD/Proxy HOD email address_DataCard3_8": {},
    "HOD/Proxy HOD email address_DataCard6_3": {},
    "HOD/Proxy HOD email address_DataCard6_4": {},
    "Host": {},
    "HR Dashboard": {},
    "Icon1": {},
    "Icon1_1": {},
    "Icon1_2": {},
    "Icon1_3": {},
    "Icon1_4": {},
    "Icon1_5": {},
    "Icon10": {},
    "Icon11_1": {},
    "Icon12_1": {},
    "Icon14": {},
    "Icon17": {},
    "Icon2": {},
    "Icon2_1": {},
    "Icon3": {},
    "Icon3_1": {},
    "Icon4": {},
    "Icon4_1": {},
    "Icon5": {},
    "Icon5_1": {},
    "Icon6": {},
    "Icon6_1": {},
    "Icon7": {},
    "Icon7_1": {},
    "Icon8": {},
    "Icon8_1": {},
    "Image1": {},
    "Image2": {},
    "Image2_1": {},
    "Image3": {},
    "Image3_1": {},
    "Image4": {},
    "Image4_1": {},
    "Image5": {},
    "Image8": {},
    "Image8_1": {},
    "Item_DataCard2_5": {},
    "Item_DataCard2_6": {},
    "Item_DataCard2_7": {},
    "Item_DataCard2_8": {},
    "Item_DataCard3": {},
    "Item_DataCard5_3": {},
    "Item_DataCard5_4": {},
    "Label1": {},
    "Label1_1": {},
    "Label10": {},
    "Label10_1": {},
    "Label10_10": {},
    "Label10_11": {},
    "Label10_12": {},
    "Label10_2": {},
    "Label10_3": {},
    "Label10_4": {},
    "Label10_5": {},
    "Label10_6": {},
    "Label10_7": {},
    "Label10_8": {},
    "Label10_9": {},
    "Label11": {},
    "Label11_1": {},
    "Label11_2": {},
    "Label11_3": {},
    "Label13": {},
    "Label13_1": {},
    "Label13_2": {},
    "Label13_3": {},
    "Label13_4": {},
    "Label13_5": {},
    "Label13_6": {},
    "Label14_1": {},
    "Label14_2": {},
    "Label15": {},
    "Label15_1": {},
    "Label15_2": {},
    "Label15_3": {},
    "Label16": {},
    "Label17": {},
    "Label2": {},
    "Label2_1": {},
    "Label2_2": {},
    "Label2_3": {},
    "Label3": {},
    "Label3_1": {},
    "Label3_2": {},
    "Label4": {},
    "Label5": {},
    "Label5_1": {},
    "Label5_2": {},
    "Label6": {},
    "Label6_2": {},
    "Label6_3": {},
    "Label7": {},
    "Label7_1": {},
    "Label8": {},
    "Label8_1": {},
    "Label9": {},
    "Label9_1": {},
    "LblAppName1_10": {},
    "LblAppName1_11": {},
    "LblAppName1_8": {},
    "LblAppName1_9": {},
    "LblAppName2_1": {},
    "LblAppName2_2": {},
    "MainContainer4": {},
    "MainContainer4_1": {},
    "MD Dashboard": {},
    "Name of Employee_DataCard2_5": {},
    "Name of Employee_DataCard2_6": {},
    "Name of Employee_DataCard2_7": {},
    "Name of Employee_DataCard2_8": {},
    "Name of Employee_DataCard3": {},
    "Name of Employee_DataCard5_3": {},
    "Name of Employee_DataCard5_4": {},
    "New Request Screen": {},
    "NextArrow1": {},
    "NextArrow1_1": {},
    "NextArrow1_2": {},
    "NextArrow1_3": {},
    "NextArrow5_2": {},
    "NextArrow5_4": {},
    "NextArrow5_5": {},
    "Overall Request": {},
    "Past Requests": {},
    "pdfPane_1": {},
    "Quantity_DataCard1": {},
    "Quantity_DataCard3_5": {},
    "Quantity_DataCard3_6": {},
    "Quantity_DataCard3_7": {},
    "Quantity_DataCard3_8": {},
    "Quantity_DataCard5_3": {},
    "Quantity_DataCard5_4": {},
    "Receipt Confirmation Screen": {},
    "Rectangle1": {},
    "Rectangle1_1": {},
    "Rectangle1_2": {},
    "Rectangle1_3": {},
    "Rectangle1_4": {},
    "Rectangle1_5": {},
    "Rectangle2": {},
    "Rectangle3": {},
    "Rectangle4": {},
    "Rectangle4_1": {},
    "Rectangle5_2": {},
    "Rectangle5_4": {},
    "Rectangle5_5": {},
    "Report": {},
    "Request Type_DataCard3": {},
    "ScreenContainer4": {},
    "ScreenContainer4_1": {},
    "Separator1": {},
    "Separator1_1": {},
    "Separator1_2": {},
    "Separator1_3": {},
    "Separator5_2": {},
    "Separator5_4": {},
    "Separator5_5": {},
    "SidebarContainer4": {},
    "SidebarContainer4_1": {},
    "StarVisible1": {},
    "StarVisible2": {},
    "StarVisible21": {},
    "StarVisible22": {},
    "StarVisible23": {},
    "StarVisible24": {},
    "StarVisible25": {},
    "StarVisible26": {},
    "StarVisible27": {},
    "StarVisible28": {},
    "StarVisible29": {},
    "StarVisible3": {},
    "StarVisible30_5": {},
    "StarVisible30_6": {},
    "StarVisible30_7": {},
    "StarVisible30_8": {},
    "StarVisible31_5": {},
    "StarVisible31_6": {},
    "StarVisible31_7": {},
    "StarVisible31_8": {},
    "StarVisible32_5": {},
    "StarVisible32_6": {},
    "StarVisible32_7": {},
    "StarVisible32_8": {},
    "StarVisible33_5": {},
    "StarVisible33_6": {},
    "StarVisible33_7": {},
    "StarVisible33_8": {},
    "StarVisible34_5": {},
    "StarVisible34_6": {},
    "StarVisible34_7": {},
    "StarVisible34_8": {},
    "StarVisible36_5": {},
    "StarVisible36_6": {},
    "StarVisible36_7": {},
    "StarVisible36_8": {},
    "StarVisible39_5": {},
    "StarVisible39_6": {},
    "StarVisible39_7": {},
    "StarVisible39_8": {},
    "StarVisible40_5": {},
    "StarVisible40_6": {},
    "StarVisible40_7": {},
    "StarVisible40_8": {},
    "StarVisible42_5": {},
    "StarVisible42_6": {},
    "StarVisible42_7": {},
    "StarVisible42_8": {},
    "StarVisible44_5": {},
    "StarVisible44_6": {},
    "StarVisible44_7": {},
    "StarVisible44_8": {},
    "StarVisible62_3": {},
    "StarVisible62_4": {},
    "StarVisible63_3": {},
    "StarVisible63_4": {},
    "StarVisible64_3": {},
    "StarVisible64_4": {},
    "StarVisible65_3": {},
    "StarVisible65_4": {},
    "StarVisible66_3": {},
    "StarVisible66_4": {},
    "StarVisible68_3": {},
    "StarVisible68_4": {},
    "StarVisible71_3": {},
    "StarVisible71_4": {},
    "StarVisible72_3": {},
    "StarVisible72_4": {},
    "StarVisible75_3": {},
    "StarVisible75_4": {},
    "StarVisible76_3": {},
    "StarVisible76_4": {},
    "StarVisible77_3": {},
    "StarVisible77_4": {},
    "Status_DataCard4_3": {},
    "Status_DataCard4_4": {},
    "Subtitle1": {},
    "Subtitle1_1": {},
    "Subtitle1_2": {},
    "Subtitle1_3": {},
    "Subtitle5_14": {},
    "Subtitle5_16": {},
    "Subtitle5_17": {},
    "Subtitle5_18": {},
    "Subtitle5_19": {},
    "Subtitle5_20": {},
    "Subtitle5_24": {},
    "Subtitle5_25": {},
    "Subtitle5_26": {},
    "Subtitle5_27": {},
    "Subtitle5_29": {},
    "Subtitle5_30": {},
    "Subtitle5_31": {},
    "Subtitle5_32": {},
    "Subtitle5_33": {},
    "Subtitle5_5": {},
    "Subtitle5_7": {},
    "Subtitle5_8": {},
    "TextInput1_1": {},
    "TextInput4": {},
    "TextInput5": {},
    "Title_DataCard3": {},
    "Title1": {},
    "Title1_1": {},
    "Title1_2": {},
    "Title1_3": {},
    "Title1_4": {},
    "Title1_5": {},
    "Title1_6": {},
    "Title1_7": {},
    "Title5_2": {},
    "Title5_4": {},
    "Title5_5": {}
  },
  "PCFDynamicSchemaForIRRetrievalEntry": {},
  "PCFTemplateEntry": {},
  "PublishOrderIndices": {
    "Amount in figures_DataCard2_5": 131,
    "Amount in figures_DataCard2_6": 190,
    "Amount in figures_DataCard2_7": 256,
    "Amount in figures_DataCard2_8": 311,
    "Amount in figures_DataCard3": 43,
    "Amount in figures_DataCard5_3": 396,
    "Amount in figures_DataCard5_4": 522,
    "Amount in words_DataCard2_5": 136,
    "Amount in words_DataCard2_6": 195,
    "Amount in words_DataCard2_7": 261,
    "Amount in words_DataCard2_8": 316,
    "Amount in words_DataCard3": 48,
    "Amount in words_DataCard5_3": 401,
    "Amount in words_DataCard5_4": 527,
    "AmountInFigures": 46,
    "App": 0,
    "approverOne": 61,
    "Arrow1_1": 579,
    "attachment": 56,
    "attachment_2": 581,
    "Attachments_DataCard2_5": 146,
    "Attachments_DataCard2_6": 210,
    "Attachments_DataCard2_7": 276,
    "Attachments_DataCard2_8": 331,
    "Attachments_DataCard4": 53,
    "Attachments_DataCard5_3": 416,
    "Attachments_DataCard5_4": 542,
    "BottomContainer4": 350,
    "BottomContainer4_1": 476,
    "Button1": 63,
    "Button1_1": 84,
    "Button1_2": 430,
    "Button2": 66,
    "Button2_1": 437,
    "Button2_3": 69,
    "Button2_4": 444,
    "Button3": 72,
    "Button3_1": 447,
    "Button4": 75,
    "Button4_1": 451,
    "Button5": 78,
    "Button5_1": 458,
    "Button5_2": 81,
    "Button5_3": 466,
    "Button6": 96,
    "Button6_1": 98,
    "Button6_2": 226,
    "Button6_3": 227,
    "Button6_4": 343,
    "Button6_5": 344,
    "Button7": 433,
    "Button7_1": 434,
    "Button7_2": 86,
    "Button7_3": 154,
    "Button7_4": 432,
    "Button7_5": 435,
    "Button7_6": 463,
    "Button7_7": 457,
    "Button7_8": 461,
    "comment": 97,
    "comment2": 228,
    "comment3": 345,
    "DataCardKey1": 10,
    "DataCardKey2": 60,
    "DataCardKey21": 5,
    "DataCardKey22": 15,
    "DataCardKey23": 35,
    "DataCardKey24": 45,
    "DataCardKey25": 50,
    "DataCardKey26": 20,
    "DataCardKey27": 25,
    "DataCardKey28": 30,
    "DataCardKey29": 55,
    "DataCardKey3": 40,
    "DataCardKey30_5": 103,
    "DataCardKey30_6": 167,
    "DataCardKey30_7": 233,
    "DataCardKey30_8": 288,
    "DataCardKey31_5": 123,
    "DataCardKey31_6": 187,
    "DataCardKey31_7": 253,
    "DataCardKey31_8": 308,
    "DataCardKey32_5": 133,
    "DataCardKey32_6": 192,
    "DataCardKey32_7": 258,
    "DataCardKey32_8": 313,
    "DataCardKey33_5": 138,
    "DataCardKey33_6": 197,
    "DataCardKey33_7": 263,
    "DataCardKey33_8": 318,
    "DataCardKey34_5": 113,
    "DataCardKey34_6": 177,
    "DataCardKey34_7": 243,
    "DataCardKey34_8": 298,
    "DataCardKey36_5": 118,
    "DataCardKey36_6": 182,
    "DataCardKey36_7": 248,
    "DataCardKey36_8": 303,
    "DataCardKey39_5": 108,
    "DataCardKey39_6": 172,
    "DataCardKey39_7": 238,
    "DataCardKey39_8": 293,
    "DataCardKey40_5": 128,
    "DataCardKey40_6": 202,
    "DataCardKey40_7": 268,
    "DataCardKey40_8": 323,
    "DataCardKey42_5": 143,
    "DataCardKey42_6": 207,
    "DataCardKey42_7": 273,
    "DataCardKey42_8": 328,
    "DataCardKey44_5": 148,
    "DataCardKey44_6": 212,
    "DataCardKey44_7": 278,
    "DataCardKey44_8": 333,
    "DataCardKey62_3": 368,
    "DataCardKey62_4": 494,
    "DataCardKey63_3": 388,
    "DataCardKey63_4": 514,
    "DataCardKey64_3": 398,
    "DataCardKey64_4": 524,
    "DataCardKey65_3": 403,
    "DataCardKey65_4": 529,
    "DataCardKey66_3": 378,
    "DataCardKey66_4": 504,
    "DataCardKey68_3": 383,
    "DataCardKey68_4": 509,
    "DataCardKey71_3": 373,
    "DataCardKey71_4": 499,
    "DataCardKey72_3": 393,
    "DataCardKey72_4": 519,
    "DataCardKey75_3": 408,
    "DataCardKey75_4": 534,
    "DataCardKey76_3": 418,
    "DataCardKey76_4": 544,
    "DataCardKey77_3": 413,
    "DataCardKey77_4": 539,
    "DataCardValue1": 11,
    "DataCardValue2": 41,
    "DataCardValue20_5": 104,
    "DataCardValue20_6": 168,
    "DataCardValue20_7": 234,
    "DataCardValue20_8": 289,
    "DataCardValue21": 6,
    "DataCardValue22": 16,
    "DataCardValue23": 36,
    "DataCardValue25": 51,
    "DataCardValue26": 21,
    "DataCardValue27": 26,
    "DataCardValue28": 31,
    "DataCardValue29_5": 124,
    "DataCardValue29_6": 188,
    "DataCardValue29_7": 254,
    "DataCardValue29_8": 309,
    "DataCardValue30_5": 134,
    "DataCardValue30_6": 193,
    "DataCardValue30_7": 259,
    "DataCardValue30_8": 314,
    "DataCardValue31_5": 139,
    "DataCardValue31_6": 198,
    "DataCardValue31_7": 264,
    "DataCardValue31_8": 319,
    "DataCardValue32_5": 114,
    "DataCardValue32_6": 178,
    "DataCardValue32_7": 244,
    "DataCardValue32_8": 299,
    "DataCardValue34_5": 119,
    "DataCardValue34_6": 183,
    "DataCardValue34_7": 249,
    "DataCardValue34_8": 304,
    "DataCardValue37_5": 109,
    "DataCardValue37_6": 173,
    "DataCardValue37_7": 239,
    "DataCardValue37_8": 294,
    "DataCardValue38_5": 129,
    "DataCardValue38_6": 203,
    "DataCardValue38_7": 269,
    "DataCardValue38_8": 324,
    "DataCardValue42_5": 149,
    "DataCardValue42_6": 213,
    "DataCardValue42_7": 279,
    "DataCardValue42_8": 334,
    "DataCardValue60_3": 369,
    "DataCardValue60_4": 495,
    "DataCardValue61_3": 389,
    "DataCardValue61_4": 515,
    "DataCardValue62_3": 399,
    "DataCardValue62_4": 525,
    "DataCardValue63_3": 404,
    "DataCardValue63_4": 530,
    "DataCardValue64_3": 379,
    "DataCardValue64_4": 505,
    "DataCardValue66_3": 384,
    "DataCardValue66_4": 510,
    "DataCardValue69_3": 374,
    "DataCardValue69_4": 500,
    "DataCardValue70_3": 394,
    "DataCardValue70_4": 520,
    "DataCardValue73_3": 409,
    "DataCardValue73_4": 535,
    "DataCardValue74_3": 419,
    "DataCardValue74_4": 545,
    "DataCardValue75_3": 414,
    "DataCardValue75_4": 540,
    "Date_DataCard1": 8,
    "Date_DataCard3_5": 106,
    "Date_DataCard3_6": 170,
    "Date_DataCard3_7": 236,
    "Date_DataCard3_8": 291,
    "Date_DataCard5_3": 371,
    "Date_DataCard5_4": 497,
    "Department_DataCard2_5": 111,
    "Department_DataCard2_6": 175,
    "Department_DataCard2_7": 241,
    "Department_DataCard2_8": 296,
    "Department_DataCard4": 18,
    "Department_DataCard5_3": 376,
    "Department_DataCard5_4": 502,
    "ErrorMessage1": 12,
    "ErrorMessage2": 62,
    "ErrorMessage21": 7,
    "ErrorMessage22": 17,
    "ErrorMessage23": 37,
    "ErrorMessage24": 47,
    "ErrorMessage25": 52,
    "ErrorMessage26": 22,
    "ErrorMessage27": 27,
    "ErrorMessage28": 32,
    "ErrorMessage29": 57,
    "ErrorMessage3": 42,
    "ErrorMessage30_5": 105,
    "ErrorMessage30_6": 169,
    "ErrorMessage30_7": 235,
    "ErrorMessage30_8": 290,
    "ErrorMessage31_5": 125,
    "ErrorMessage31_6": 189,
    "ErrorMessage31_7": 255,
    "ErrorMessage31_8": 310,
    "ErrorMessage32_5": 135,
    "ErrorMessage32_6": 194,
    "ErrorMessage32_7": 260,
    "ErrorMessage32_8": 315,
    "ErrorMessage33_5": 140,
    "ErrorMessage33_6": 199,
    "ErrorMessage33_7": 265,
    "ErrorMessage33_8": 320,
    "ErrorMessage34_5": 115,
    "ErrorMessage34_6": 179,
    "ErrorMessage34_7": 245,
    "ErrorMessage34_8": 300,
    "ErrorMessage36_5": 120,
    "ErrorMessage36_6": 184,
    "ErrorMessage36_7": 250,
    "ErrorMessage36_8": 305,
    "ErrorMessage39_5": 110,
    "ErrorMessage39_6": 174,
    "ErrorMessage39_7": 240,
    "ErrorMessage39_8": 295,
    "ErrorMessage40_5": 130,
    "ErrorMessage40_6": 204,
    "ErrorMessage40_7": 270,
    "ErrorMessage40_8": 325,
    "ErrorMessage42_5": 145,
    "ErrorMessage42_6": 209,
    "ErrorMessage42_7": 275,
    "ErrorMessage42_8": 330,
    "ErrorMessage44_5": 150,
    "ErrorMessage44_6": 214,
    "ErrorMessage44_7": 280,
    "ErrorMessage44_8": 335,
    "ErrorMessage62_3": 370,
    "ErrorMessage62_4": 496,
    "ErrorMessage63_3": 390,
    "ErrorMessage63_4": 516,
    "ErrorMessage64_3": 400,
    "ErrorMessage64_4": 526,
    "ErrorMessage65_3": 405,
    "ErrorMessage65_4": 531,
    "ErrorMessage66_3": 380,
    "ErrorMessage66_4": 506,
    "ErrorMessage68_3": 385,
    "ErrorMessage68_4": 511,
    "ErrorMessage71_3": 375,
    "ErrorMessage71_4": 501,
    "ErrorMessage72_3": 395,
    "ErrorMessage72_4": 521,
    "ErrorMessage75_3": 410,
    "ErrorMessage75_4": 536,
    "ErrorMessage76_3": 420,
    "ErrorMessage76_4": 546,
    "ErrorMessage77_3": 415,
    "ErrorMessage77_4": 541,
    "Expense Category_DataCard2_5": 116,
    "Expense Category_DataCard2_6": 180,
    "Expense Category_DataCard2_7": 246,
    "Expense Category_DataCard2_8": 301,
    "Expense Category_DataCard3": 28,
    "Expense Category_DataCard5_3": 381,
    "Expense Category_DataCard5_4": 507,
    "Form1": 2,
    "Form3_5": 100,
    "Form3_6": 164,
    "Form3_7": 230,
    "Form3_8": 285,
    "Form5_3": 365,
    "Form5_4": 491,
    "Gallery1": 89,
    "Gallery1_1": 156,
    "Gallery1_2": 219,
    "Gallery1_3": 336,
    "Gallery5_2": 352,
    "Gallery5_4": 478,
    "Gallery5_5": 583,
    "galleryTemplate1": 90,
    "galleryTemplate1_1": 157,
    "galleryTemplate1_2": 220,
    "galleryTemplate1_3": 337,
    "galleryTemplate5_2": 353,
    "galleryTemplate5_4": 479,
    "galleryTemplate5_5": 584,
    "HeaderContainer4": 348,
    "HeaderContainer4_1": 473,
    "HOD Dashboard": 0,
    "HOD Dashboard_Pending": 0,
    "HOD email address_1": 144,
    "HOD email address_2": 208,
    "HOD email address_3": 274,
    "HOD email address_4": 329,
    "HOD/Proxy HOD email address_DataCard1": 58,
    "HOD/Proxy HOD email address_DataCard3_5": 141,
    "HOD/Proxy HOD email address_DataCard3_6": 205,
    "HOD/Proxy HOD email address_DataCard3_7": 271,
    "HOD/Proxy HOD email address_DataCard3_8": 326,
    "HOD/Proxy HOD email address_DataCard6_3": 411,
    "HOD/Proxy HOD email address_DataCard6_4": 537,
    "Host": 0,
    "HR Dashboard": 0,
    "Icon1": 64,
    "Icon1_1": 431,
    "Icon1_2": 87,
    "Icon1_3": 153,
    "Icon1_4": 218,
    "Icon1_5": 283,
    "Icon10": 551,
    "Icon11_1": 582,
    "Icon12_1": 580,
    "Icon14": 469,
    "Icon17": 82,
    "Icon2": 73,
    "Icon2_1": 448,
    "Icon3": 67,
    "Icon3_1": 441,
    "Icon4": 70,
    "Icon4_1": 445,
    "Icon5": 421,
    "Icon5_1": 547,
    "Icon6": 423,
    "Icon6_1": 549,
    "Icon7": 76,
    "Icon7_1": 452,
    "Icon8": 80,
    "Icon8_1": 460,
    "Image1": 1,
    "Image2": 151,
    "Image2_1": 555,
    "Image3": 216,
    "Image3_1": 282,
    "Image4": 422,
    "Image4_1": 548,
    "Image5": 426,
    "Image8": 424,
    "Image8_1": 552,
    "Item_DataCard2_5": 121,
    "Item_DataCard2_6": 185,
    "Item_DataCard2_7": 251,
    "Item_DataCard2_8": 306,
    "Item_DataCard3": 33,
    "Item_DataCard5_3": 386,
    "Item_DataCard5_4": 512,
    "Label1": 65,
    "Label1_1": 436,
    "Label10": 557,
    "Label10_1": 558,
    "Label10_10": 571,
    "Label10_11": 572,
    "Label10_12": 561,
    "Label10_2": 559,
    "Label10_3": 560,
    "Label10_4": 562,
    "Label10_5": 564,
    "Label10_6": 566,
    "Label10_7": 565,
    "Label10_8": 568,
    "Label10_9": 569,
    "Label11": 563,
    "Label11_1": 567,
    "Label11_2": 570,
    "Label11_3": 573,
    "Label13": 456,
    "Label13_1": 450,
    "Label13_2": 455,
    "Label13_3": 454,
    "Label13_4": 471,
    "Label13_5": 470,
    "Label13_6": 464,
    "Label14_1": 576,
    "Label14_2": 575,
    "Label15": 439,
    "Label15_1": 465,
    "Label15_2": 443,
    "Label15_3": 462,
    "Label16": 467,
    "Label17": 428,
    "Label2": 68,
    "Label2_1": 442,
    "Label2_2": 71,
    "Label2_3": 446,
    "Label3": 77,
    "Label3_1": 453,
    "Label3_2": 468,
    "Label4": 556,
    "Label5": 79,
    "Label5_1": 459,
    "Label5_2": 83,
    "Label6": 438,
    "Label6_2": 88,
    "Label6_3": 155,
    "Label7": 440,
    "Label7_1": 217,
    "Label8": 74,
    "Label8_1": 449,
    "Label9": 429,
    "Label9_1": 284,
    "LblAppName1_10": 215,
    "LblAppName1_11": 281,
    "LblAppName1_8": 85,
    "LblAppName1_9": 152,
    "LblAppName2_1": 349,
    "LblAppName2_2": 474,
    "MainContainer4": 364,
    "MainContainer4_1": 490,
    "MD Dashboard": 0,
    "Name of Employee_DataCard2_5": 101,
    "Name of Employee_DataCard2_6": 165,
    "Name of Employee_DataCard2_7": 231,
    "Name of Employee_DataCard2_8": 286,
    "Name of Employee_DataCard3": 13,
    "Name of Employee_DataCard5_3": 366,
    "Name of Employee_DataCard5_4": 492,
    "New Request Screen": 0,
    "NextArrow1": 94,
    "NextArrow1_1": 162,
    "NextArrow1_2": 224,
    "NextArrow1_3": 341,
    "NextArrow5_2": 358,
    "NextArrow5_4": 484,
    "NextArrow5_5": 589,
    "Overall Request": 0,
    "Past Requests": 0,
    "pdfPane_1": 554,
    "Quantity_DataCard1": 38,
    "Quantity_DataCard3_5": 126,
    "Quantity_DataCard3_6": 200,
    "Quantity_DataCard3_7": 266,
    "Quantity_DataCard3_8": 321,
    "Quantity_DataCard5_3": 391,
    "Quantity_DataCard5_4": 517,
    "Receipt Confirmation Screen": 0,
    "Rectangle1": 91,
    "Rectangle1_1": 0,
    "Rectangle1_2": 425,
    "Rectangle1_3": 158,
    "Rectangle1_4": 221,
    "Rectangle1_5": 338,
    "Rectangle2": 427,
    "Rectangle3": 574,
    "Rectangle4": 577,
    "Rectangle4_1": 578,
    "Rectangle5_2": 354,
    "Rectangle5_4": 480,
    "Rectangle5_5": 585,
    "Report": 0,
    "Request Type_DataCard3": 23,
    "ScreenContainer4": 347,
    "ScreenContainer4_1": 472,
    "Separator1": 99,
    "Separator1_1": 163,
    "Separator1_2": 229,
    "Separator1_3": 346,
    "Separator5_2": 363,
    "Separator5_4": 489,
    "Separator5_5": 594,
    "SidebarContainer4": 351,
    "SidebarContainer4_1": 477,
    "StarVisible1": 9,
    "StarVisible2": 59,
    "StarVisible21": 4,
    "StarVisible22": 14,
    "StarVisible23": 34,
    "StarVisible24": 44,
    "StarVisible25": 49,
    "StarVisible26": 19,
    "StarVisible27": 24,
    "StarVisible28": 29,
    "StarVisible29": 54,
    "StarVisible3": 39,
    "StarVisible30_5": 102,
    "StarVisible30_6": 166,
    "StarVisible30_7": 232,
    "StarVisible30_8": 287,
    "StarVisible31_5": 122,
    "StarVisible31_6": 186,
    "StarVisible31_7": 252,
    "StarVisible31_8": 307,
    "StarVisible32_5": 132,
    "StarVisible32_6": 191,
    "StarVisible32_7": 257,
    "StarVisible32_8": 312,
    "StarVisible33_5": 137,
    "StarVisible33_6": 196,
    "StarVisible33_7": 262,
    "StarVisible33_8": 317,
    "StarVisible34_5": 112,
    "StarVisible34_6": 176,
    "StarVisible34_7": 242,
    "StarVisible34_8": 297,
    "StarVisible36_5": 117,
    "StarVisible36_6": 181,
    "StarVisible36_7": 247,
    "StarVisible36_8": 302,
    "StarVisible39_5": 107,
    "StarVisible39_6": 171,
    "StarVisible39_7": 237,
    "StarVisible39_8": 292,
    "StarVisible40_5": 127,
    "StarVisible40_6": 201,
    "StarVisible40_7": 267,
    "StarVisible40_8": 322,
    "StarVisible42_5": 142,
    "StarVisible42_6": 206,
    "StarVisible42_7": 272,
    "StarVisible42_8": 327,
    "StarVisible44_5": 147,
    "StarVisible44_6": 211,
    "StarVisible44_7": 277,
    "StarVisible44_8": 332,
    "StarVisible62_3": 367,
    "StarVisible62_4": 493,
    "StarVisible63_3": 387,
    "StarVisible63_4": 513,
    "StarVisible64_3": 397,
    "StarVisible64_4": 523,
    "StarVisible65_3": 402,
    "StarVisible65_4": 528,
    "StarVisible66_3": 377,
    "StarVisible66_4": 503,
    "StarVisible68_3": 382,
    "StarVisible68_4": 508,
    "StarVisible71_3": 372,
    "StarVisible71_4": 498,
    "StarVisible72_3": 392,
    "StarVisible72_4": 518,
    "StarVisible75_3": 407,
    "StarVisible75_4": 533,
    "StarVisible76_3": 417,
    "StarVisible76_4": 543,
    "StarVisible77_3": 412,
    "StarVisible77_4": 538,
    "Status_DataCard4_3": 406,
    "Status_DataCard4_4": 532,
    "Subtitle1": 93,
    "Subtitle1_1": 160,
    "Subtitle1_2": 223,
    "Subtitle1_3": 340,
    "Subtitle5_14": 357,
    "Subtitle5_16": 483,
    "Subtitle5_17": 588,
    "Subtitle5_18": 359,
    "Subtitle5_19": 360,
    "Subtitle5_20": 361,
    "Subtitle5_24": 485,
    "Subtitle5_25": 486,
    "Subtitle5_26": 487,
    "Subtitle5_27": 362,
    "Subtitle5_29": 488,
    "Subtitle5_30": 590,
    "Subtitle5_31": 592,
    "Subtitle5_32": 593,
    "Subtitle5_33": 591,
    "Subtitle5_5": 355,
    "Subtitle5_7": 481,
    "Subtitle5_8": 586,
    "TextInput1_1": 553,
    "TextInput4": 475,
    "TextInput5": 550,
    "Title_DataCard3": 3,
    "Title1": 92,
    "Title1_1": 95,
    "Title1_2": 159,
    "Title1_3": 161,
    "Title1_4": 222,
    "Title1_5": 225,
    "Title1_6": 339,
    "Title1_7": 342,
    "Title5_2": 356,
    "Title5_4": 482,
    "Title5_5": 587
  },
  "ResourcesJsonIndices": {
    "Image-3652191": 1,
    "Image-4221459": 2,
    "Image-approve-badge-4715768": 6,
    "Image-approved-checklist-5588674": 5,
    "Image-check-profile-4715752": 7,
    "Image-DD": 10,
    "Image-dd white": 9,
    "Image-images": 3,
    "Image-nr1": 4,
    "Image-SampleImage": 0,
    "Image-verified-calendar-5575938": 8,
    "Pdf-SamplePdf": 11
  },
  "RuleScreenIdWithoutScreen": {},
  "TemplateVersions": {},
  "VolatileProperties": {
    "AnalysisLoadTime": 3.2861644,
    "ControlCount": {
      "arrow": 1,
      "attachments": 8,
      "button": 30,
      "combobox": 22,
      "datepicker": 7,
      "form": 7,
      "gallery": 7,
      "galleryTemplate": 7,
      "groupContainer": 11,
      "icon": 32,
      "image": 10,
      "label": 315,
      "rectangle": 20,
      "screen": 9,
      "text": 44,
      "typedDataCard": 74
    },
    "DeserializationLoadTime": 4.0549556
  },
  "WasLocalDatabaseReferencesEmpty": true
}